CHANGES.txt
CONTRIBUTORS.txt
MANIFEST.in
README.txt
setup.py
gp/__init__.py
gp.recipe.pip.egg-info/PKG-INFO
gp.recipe.pip.egg-info/SOURCES.txt
gp.recipe.pip.egg-info/dependency_links.txt
gp.recipe.pip.egg-info/entry_points.txt
gp.recipe.pip.egg-info/namespace_packages.txt
gp.recipe.pip.egg-info/not-zip-safe
gp.recipe.pip.egg-info/requires.txt
gp.recipe.pip.egg-info/top_level.txt
gp/recipe/__init__.py
gp/recipe/pip/README.txt
gp/recipe/pip/__init__.py
gp/recipe/pip/tests.txt
gp/recipe/pip/tests/__init__.py
gp/recipe/pip/tests/test_docs.py