Metadata-Version: 1.0
Name: gp.recipe.pip
Version: 0.5.2
Summary: zc.buildout recipe for pip
Home-page: http://www.bitbucket.org/gawel/gprecipepip/
Author: Gael Pasgrimaud
Author-email: gael@gawel.org
License: MIT
Keywords: buildout pip
Platform: UNKNOWN
Classifier: Framework :: Buildout
Classifier: Intended Audience :: Developers
Classifier: Topic :: Software Development :: Build Tools
Classifier: Topic :: Software Development :: Libraries :: Python Modules
Classifier: License :: OSI Approved :: MIT License
